asyncsip/__init__.py
asyncsip/application.py
asyncsip/auth.py
asyncsip/contact.py
asyncsip/dialog.py
asyncsip/dialplan.py
asyncsip/exceptions.py
asyncsip/message.py
asyncsip/param.py
asyncsip/peers.py
asyncsip/protocol.py
asyncsip/pytest_plugin.py
asyncsip/transaction.py
asyncsip/uri.py
asyncsip/utils.py
asyncsip/via.py
asyncsip-0.1.2.dist-info/AUTHORS.rst
asyncsip-0.1.2.dist-info/LICENSE
asyncsip-0.1.2.dist-info/METADATA
asyncsip-0.1.2.dist-info/WHEEL
asyncsip-0.1.2.dist-info/top_level.txt
asyncsip-0.1.2.dist-info/RECORD
