Metadata-Version: 2.1
Name: asyncsip
Version: 0.1.2
Summary: SIP support for AsyncIO
Home-page: https://github.com/MoronVV/asyncsip
Author: Vlad Veselov (moronvv)
Author-email: moronvv@gmail.com
License: Apache 2
Keywords: asyncio,sip,telephony
Platform: UNKNOWN
Classifier: Development Status :: 3 - Alpha
Classifier: Framework :: AsyncIO
Classifier: Intended Audience :: Developers
Classifier: License :: OSI Approved :: Apache Software License
Classifier: Natural Language :: English
Classifier: Programming Language :: Python :: 3
Classifier: Programming Language :: Python :: 3.6
Classifier: Topic :: Communications
Classifier: Topic :: Communications :: Internet Phone
Classifier: Topic :: Communications :: Telephony
Requires-Dist: multidict (>=2.0)
Requires-Dist: pyquery
Requires-Dist: aiodns
Requires-Dist: websockets
Requires-Dist: async-timeout
